videosdk/plugins/cerebras/__init__.py
videosdk/plugins/cerebras/llm.py
videosdk/plugins/cerebras/version.py
videosdk_plugins_cerebras-0.0.58.dist-info/METADATA
videosdk_plugins_cerebras-0.0.58.dist-info/WHEEL
videosdk_plugins_cerebras-0.0.58.dist-info/RECORD
