Metadata-Version: 2.4
Name: videosdk-plugins-cerebras
Version: 0.0.58
Summary: VideoSDK Agent Framework plugin for Cerebras services
Author: videosdk
Keywords: ai,audio,cerebras,llm,video,videosdk
Classifier: Development Status :: 4 - Beta
Classifier: Intended Audience :: Developers
Classifier: Topic :: Communications :: Conferencing
Classifier: Topic :: Multimedia :: Sound/Audio
Classifier: Topic :: Multimedia :: Video
Classifier: Topic :: Scientific/Engineering :: Artificial Intelligence
Requires-Python: >=3.11
Requires-Dist: cerebras-cloud-sdk>=1.0.0
Requires-Dist: videosdk-agents>=0.0.58
